LICENSE
MANIFEST.in
README.md
requirements.txt
setup.py
keepassxc_pwned/__init__.py
keepassxc_pwned/__main__.py
keepassxc_pwned/cache.py
keepassxc_pwned/cli.py
keepassxc_pwned/exceptions.py
keepassxc_pwned/keepass_wrapper.py
keepassxc_pwned/log.py
keepassxc_pwned/parser.py
keepassxc_pwned/password.py
keepassxc_pwned/utils.py
keepassxc_pwned.egg-info/PKG-INFO
keepassxc_pwned.egg-info/SOURCES.txt
keepassxc_pwned.egg-info/dependency_links.txt
keepassxc_pwned.egg-info/entry_points.txt
keepassxc_pwned.egg-info/requires.txt
keepassxc_pwned.egg-info/top_level.txt
keepassxc_pwned.egg-info/zip-safe