Metadata-Version: 2.1
Name: keepassxc-pwned
Version: 0.3.0
Summary: Check your keepassxc database against previously breached haveibeenpwned passwords
Home-page: https://github.com/seanbreckenridge/keepassxc-pwned
Author: Sean Breckenridge
Author-email: seanbrecke@gmail.com
License: MIT
Keywords: keepassxc password-strength password
Platform: UNKNOWN
Classifier: Development Status :: 3 - Alpha
Classifier: Intended Audience :: End Users/Desktop
Classifier: Natural Language :: English
Classifier: Programming Language :: Python :: 3.6
Classifier: Programming Language :: Python :: 3.7
Classifier: Programming Language :: Python :: 3.8
Classifier: Programming Language :: Python :: 3.9
